pysimi/__init__.py
pysimi/api.py
pysimi/algorithms/__init__.py
pysimi/algorithms/lpp.py
pysimi/algorithms/spectral.py
pysimi/algorithms/tsne.py
pysimi/algorithms/umap_im.py
pysimi/similarities/__init__.py
pysimi/similarities/base.py
pysimi/similarities/pairwise.py
pysimi/similarities/classic/__init__.py
pysimi/similarities/classic/correlation.py
pysimi/similarities/classic/cosine.py
pysimi/similarities/classic/polynomial.py
pysimi/similarities/classic/rbf.py
pysimi/similarities/classic/sigmoid.py
pysimi/similarities/special/__init__.py
pysimi/similarities/special/adaptive.py
pysimi/similarities/special/csnn.py
pysimi/similarities/special/density_adaptive.py
pysimi/similarities/special/iSNN.py
pysimi/similarities/special/kernel_adaptive.py
pysimi/similarities/special/nsnn.py
pysimi/similarities/special/sckNN.py
pysimi/similarities/special/self_tuning.py
pysimi_toolkit-0.1.1.dist-info/licenses/LICENSE
pysimi_toolkit-0.1.1.dist-info/METADATA
pysimi_toolkit-0.1.1.dist-info/WHEEL
pysimi_toolkit-0.1.1.dist-info/top_level.txt
pysimi_toolkit-0.1.1.dist-info/RECORD
