Metadata-Version: 2.4
Name: pysimi-toolkit
Version: 0.1.1
Summary: PySimi: a unified framework for similarity matrix construction
Author-email: Tianyi Shi <s2430153@u.tsukuba.ac.jp>
License: MIT License
Project-URL: Homepage, https://github.com/Tianyi-Shi-Tsukuba/PySimi
Project-URL: Repository, https://github.com/Tianyi-Shi-Tsukuba/PySimi
Project-URL: Issues, https://github.com/Tianyi-Shi-Tsukuba/PySimi
Keywords: similarity matrix,spectral clustering,dimensionality reduction
Classifier: Programming Language :: Python :: 3
Classifier: Programming Language :: Python :: 3 :: Only
Classifier: License :: OSI Approved :: MIT License
Classifier: Operating System :: OS Independent
Classifier: Intended Audience :: Science/Research
Classifier: Topic :: Scientific/Engineering :: Artificial Intelligence
Requires-Python: >=3.9
License-File: LICENSE
Requires-Dist: numpy>=1.20
Requires-Dist: scipy>=1.7
Requires-Dist: scikit-learn>=1.0
Requires-Dist: pandas>=1.3
Dynamic: license-file
